RighiDiary/__init__.py
RighiDiary/_agenda.py
RighiDiary/_auth_functions.py
RighiDiary/_authorize_user.py
RighiDiary/_baseprofile.py
RighiDiary/_current_year.py
RighiDiary/_homework.py
RighiDiary/_marks.py
RighiDiary/_schedule.py
RighiDiary/_user.py
RighiDiary-1.0.dist-info/LICENSE
RighiDiary-1.0.dist-info/METADATA
RighiDiary-1.0.dist-info/WHEEL
RighiDiary-1.0.dist-info/top_level.txt
RighiDiary-1.0.dist-info/RECORD
