Metadata-Version: 2.1
Name: RighiDiary
Version: 1.0
Summary: Obtaining data from the electronic diary of the lyceum "Liceo Scientifico A. Righi"
Home-page: https://github.com/Komo4ekoI/RighiRegisterAPI
Author: Vadym Teliatnyk
Author-email: laivhakin@gmail.com
Project-URL: Documentation, https://github.com/Komo4ekoI/RighiRegisterAPI
Project-URL: Bug Reports, https://github.com/Komo4ekoI/RighiRegisterAPI/issues
Project-URL: Source Code, https://github.com/Komo4ekoI/RighiRegisterAPI
Keywords: example,pypi,package,righi,righiAPI,register,diary
Classifier: Development Status :: 5 - Production/Stable
Classifier: Intended Audience :: Developers
Classifier: Topic :: Communications
Classifier: Programming Language :: Python :: 3
Classifier: Programming Language :: Python :: 3.7
Classifier: Programming Language :: Python :: 3.8
Classifier: Programming Language :: Python :: 3.9
Classifier: Programming Language :: Python :: 3 :: Only
Classifier: License :: OSI Approved :: MIT License
Classifier: Operating System :: OS Independent
Requires-Python: >=3.7
License-File: LICENSE
Requires-Dist: aiohttp >=3.8.5
Requires-Dist: beautifulsoup4 >=4.12.2
Provides-Extra: dev
Requires-Dist: check-manifest ; extra == 'dev'
